couscous/__init__.py
couscous/_nbdev.py
couscous/core.py
cousie/__init__.py
cousie/_nbdev.py
cousie/core.py
cousie-0.0.4.dist-info/LICENSE
cousie-0.0.4.dist-info/METADATA
cousie-0.0.4.dist-info/WHEEL
cousie-0.0.4.dist-info/entry_points.txt
cousie-0.0.4.dist-info/top_level.txt
cousie-0.0.4.dist-info/RECORD
